{
  "version": "1",
  "cognitoConfig": {
    "identityPoolName": "divvy73bb5d51_identitypool_73bb5d51",
    "allowUnauthenticatedIdentities": false,
    "resourceNameTruncated": "divvy73bb5d51",
    "userPoolName": "divvy73bb5d51_userpool_73bb5d51",
    "autoVerifiedAttributes": [
      "email"
    ],
    "mfaConfiguration": "OFF",
    "mfaTypes": [
      "SMS Text Message"
    ],
    "smsAuthenticationMessage": "Your authentication code is {####}",
    "smsVerificationMessage": "Your verification code is {####}",
    "emailVerificationSubject": "Your verification code",
    "emailVerificationMessage": "Your verification code is {####}",
    "defaultPasswordPolicy": false,
    "passwordPolicyMinLength": 8,
    "passwordPolicyCharacters": [],
    "requiredAttributes": [
      "email",
      "nickname"
    ],
    "aliasAttributes": [],
    "userpoolClientGenerateSecret": false,
    "userpoolClientRefreshTokenValidity": 30,
    "userpoolClientWriteAttributes": [
      "email"
    ],
    "userpoolClientReadAttributes": [
      "email"
    ],
    "userpoolClientLambdaRole": "divvy773bb5d51_userpoolclient_lambda_role",
    "userpoolClientSetAttributes": false,
    "sharedId": "73bb5d51",
    "resourceName": "divvy73bb5d51",
    "authSelections": "identityPoolAndUserPool",
    "useDefault": "default",
    "usernameAttributes": [
      "email"
    ],
    "triggers": {},
    "userPoolGroupList": [],
    "serviceName": "Cognito",
    "usernameCaseSensitive": false,
    "useEnabledMfas": true
  }
}